MultiGATE/MultiGATE.py
MultiGATE/Train_MultiGATE.py
MultiGATE/WNN_comp.py
MultiGATE/__init__.py
MultiGATE/genomics.py
MultiGATE/model_MultiGATE.py
MultiGATE/utils.py
multigate-0.0.23.dist-info/licenses/LICENSE
multigate-0.0.23.dist-info/METADATA
multigate-0.0.23.dist-info/WHEEL
multigate-0.0.23.dist-info/top_level.txt
multigate-0.0.23.dist-info/RECORD
