Metadata-Version: 2.4
Name: MultiGATE
Version: 0.0.23
Summary: MultiGATE single cell
Author-email: Jinzhao LI <jishuaimiao@gmail.com>, Jishuai MIAO <jishuaimiao@gmail.com>
License: MIT
Classifier: License :: OSI Approved :: Apache Software License
Classifier: Programming Language :: Python :: 3.7
Classifier: Operating System :: OS Independent
Requires-Python: ==3.7.*
License-File: LICENSE
Requires-Dist: tensorflow-gpu==1.15.0
Requires-Dist: scikit-learn>=1.0.2
Requires-Dist: pandas>=1.3.5
Requires-Dist: scanpy>=1.9.3
Requires-Dist: jupyterlab>=3.6.7
Requires-Dist: tqdm>=4.66.2
Requires-Dist: matplotlib>=3.5.3
Requires-Dist: networkx>=2.6
Requires-Dist: pybedtools>=0.9.0
Requires-Dist: seaborn>=0.12.2
Requires-Dist: numpy>=1.21.6
Requires-Dist: scipy>=1.7.3
Requires-Dist: nvidia-ml-py3>=7.352.0
Requires-Dist: gseapy>=1.0.4
Requires-Dist: rpy2>=3.5.16
Requires-Dist: louvain>=0.8.0
Provides-Extra: dev
Requires-Dist: pytest>=7.0; extra == "dev"
Requires-Dist: twine>=4.0.2; extra == "dev"
Dynamic: license-file
